Workbook

Sheet SUPUESTOS
A1: HOJA DE SUPUESTOS — PARÁMETROS GENERALES
B3: PARÁMETROS GENERALES
B4: Cotización USD (Gs/USD) | C4: 6500 | E4: Tipo cambio BCP referencial
B5: Imprevisto (%) | C5: 0.1 | E5: Colchón operativo sobre subtotal directo
B6: Retención IVA (%) | C6: 0.07 | E6: Retención DNIT
B7: Anticipo (%) | C7: 0.5 | E7: Política comercial fija — todos los clientes
B8: Saldo contra entrega (%) | C8: 0.5 | E8: Contra entrega de informe final
B11: DATOS DEL PROYECTO
B12: Nombre del proyecto | C12: Estancia Santa Isabel - Barrenada
B13: Nº Calicatas | C13: 11
B14: Muestras por calicata | C14: 3
B15: Nº Barrenadas | C15: 11
B16: Muestras por barrenada | C16: 1
B17: Total muestras calicatas | C17: =C13*C14 -> 33
B18: Total muestras barrenadas | C18: =C15*C16 -> 11
B19: Total muestras | C19: =C17+C18 -> 44
B20: Superficie (ha) | C20: 2000
B21: Densidad (ha/calicata) | C21: =IF(C13=0,0,C20/C13) -> 181.81818
B23: MOVILIDAD Y LOGÍSTICA
B24: Nº Vehículos | C24: 2 | E24: Camionetas 4x4
B25: Días de campo | C25: 4 | E25: Duración trabajo de campo
B26: Días totales (incl. traslado) | C26: 5 | E26: Campo + movilización
B27: Km por viaje (ida+vuelta) | C27: 350 | E27: Distancia al sitio + recorridos internos
B28: Nº Viajes | C28: 2 | E28: Viajes totales durante el proyecto
B29: Consumo (L/100km) | C29: 12 | E29: Consumo estimado camioneta 4x4
B30: Precio combustible (Gs/L) | C30: 9000 | E30: Precio actual gasoil
B31: Precio alquiler/día (Gs) | C31: =110*C4 -> 715000 | E31: 110 USD/día × cotización
B32: Nº Personas equipo campo | C32: 4 | E32: Para cálculo de viáticos
B33: Viático/persona/día (Gs) | C33: 100000 | E33: Alimentación
B34: Hospedaje/persona/día (Gs) | C34: 100000 | E34: Alojamiento rural
B36: CÁLCULOS AUXILIARES (no editar)
B37: Litros por viaje (1 vehículo) | C37: =C29*(C27/100) -> 42
B38: Litros con 20% reserva | C38: =C37*1.2 -> 50.4
B39: Costo combustible total | C39: =C38*C28*C30*C24 -> 1814400
B40: Costo alquiler total | C40: =C31*C25*C24 -> 5720000
B41: Costo viáticos total | C41: =C33*C32*C26 -> 2000000
B42: Costo hospedaje total | C42: =C34*C32*C26 -> 2000000
B44: Verificación pagos (debe ser 100%) | C44: =C7+C8 -> 1

Sheet Preparación_campo
A1: PREPARACIÓN / DESCRIPCIÓN DE CALICATAS — COSTOS DE CAMPO
A3: Nº | B3: Categoría | C3: Concepto | D3: Cant. | E3: Unidad | F3: Días | G3: Costo Unit. (Gs) | H3: Subtotal (Gs) | I3: Subtotal (USD) | J3: %
B4: HONORARIOS PROFESIONALES
A5: 1.1 | B5: Honorarios Profesional Senior | C5: Dr. Arnulfo Encina | D5: 1 | E5: Por calicata | G5: 1500000 | H5: =G5*SUPUESTOS!C13 -> 16500000 | I5: =H5/SUPUESTOS!$C$4 -> 2538.4615
A6: 1.2 | B6: Honorarios Coordinador Campo | C6: David Leckie | D6: 1 | E6: Honorario fijo | F6: 1 | G6: 5000000 | H6: =D6*F6*G6 -> 5000000 | I6: =H6/SUPUESTOS!$C$4 -> 769.23077
A7: 1.3 | B7: Honorarios | C7: Técnico 2 | D7: 1 | E7: Honorario fijo | F7: 1 | G7: 2000000 | H7: =D7*F7*G7 -> 2000000 | I7: =H7/SUPUESTOS!$C$4 -> 307.69231
A8: 1.4 | B8: Honorarios | C8: Técnico 3 | D8: 0 | E8: Honorario fijo | F8: 0 | G8: 0 | H8: =D8*F8*G8 -> 0 | I8: =H8/SUPUESTOS!$C$4 -> 0
A9: 1.5 | B9: Honorarios | C9: Ayudante 1 | D9: 1 | E9: Honorario fijo | F9: 1 | G9: 600000 | H9: =D9*F9*G9 -> 600000 | I9: =H9/SUPUESTOS!$C$4 -> 92.307692
A10: 1.6 | B10: Honorarios | C10: Ayudante 2 | D10: 1 | E10: Honorario fijo | F10: 1 | G10: 600000 | H10: =D10*F10*G10 -> 600000 | I10: =H10/SUPUESTOS!$C$4 -> 92.307692
A11: 1.7 | B11: Honorarios | C11: Ayudante 3 | D11: 0 | E11: Honorario fijo | F11: 0 | G11: 0 | H11: =D11*F11*G11 -> 0 | I11: =H11/SUPUESTOS!$C$4 -> 0
B12: Subtotal | H12: =SUM(H5:H11) -> 24700000 | I12: =H12/SUPUESTOS!$C$4 -> 3800 | J12: =IF(H$35=0,0,H12/H$35) -> 0.63239357
B13: MOVILIDAD
A14: 2.1 | B14: Movilidad | C14: Alquiler de vehículo | E14: Camioneta 4x4 | H14: =SUPUESTOS!C40 -> 5720000 | I14: =H14/SUPUESTOS!$C$4 -> 880
A15: 2.2 | B15: Movilidad | C15: Combustible | E15: Global | H15: =SUPUESTOS!C39 -> 1814400 | I15: =H15/SUPUESTOS!$C$4 -> 279.13846
B16: Subtotal | H16: =SUM(H14:H15) -> 7534400 | I16: =H16/SUPUESTOS!$C$4 -> 1159.1385 | J16: =IF(H$35=0,0,H16/H$35) -> 0.19290308
B17: VIÁTICOS / HOSPEDAJE
A18: 3.1 | B18: Viáticos | C18: Consumición | E18: Global | H18: =SUPUESTOS!C41 -> 2000000 | I18: =H18/SUPUESTOS!$C$4 -> 307.69231
A19: 3.2 | B19: Viáticos | C19: Hospedaje | E19: Global | H19: =SUPUESTOS!C42 -> 2000000 | I19: =H19/SUPUESTOS!$C$4 -> 307.69231
B20: Subtotal | H20: =SUM(H18:H19) -> 4000000 | I20: =H20/SUPUESTOS!$C$4 -> 615.38462 | J20: =IF(H$35=0,0,H20/H$35) -> 0.10241191
B21: USO DE EQUIPOS
A22: 4.1 | B22: Equipos | C22: Penetrómetro | D22: 2 | E22: Unidad | F22: 1 | H22: =D22*F22*Equipos!E2 -> 208000 | I22: =H22/SUPUESTOS!$C$4 -> 32
A23: 4.2 | B23: Equipos | C23: Dron | D23: 1 | E23: Unidad | F23: 8 | H23: =D23*F23*Equipos!E3 -> 1066666.7 | I23: =H23/SUPUESTOS!$C$4 -> 164.10256
A24: 4.3 | B24: Equipos | C24: Cilindro | D24: 0 | E24: Paq. 10 cilindros | F24: 0 | G24: 40000 | H24: =D24*F24*G24 -> 0 | I24: =H24/SUPUESTOS!$C$4 -> 0
A25: 4.4 | B25: Equipos | C25: Cámara digital | D25: 1 | E25: Unidad | F25: 8 | H25: =D25*F25*Equipos!E4 -> 400000 | I25: =H25/SUPUESTOS!$C$4 -> 61.538462
A26: 4.5 | B26: Equipos | C26: Tablet | D26: 1 | E26: Unidad | F26: 8 | H26: =D26*F26*Equipos!E5 -> 488888.89 | I26: =H26/SUPUESTOS!$C$4 -> 75.213675
B27: Subtotal | H27: =SUM(H22:H26) -> 2163555.6 | I27: =H27/SUPUESTOS!$C$4 -> 332.8547 | J27: =IF(H$35=0,0,H27/H$35) -> 0.055393467
B28: OTROS GASTOS
A29: 5.1 | B29: Otros | C29: Gabinete (impresiones) | D29: 0 | E29: Global | F29: 1 | G29: 100000 | H29: =D29*F29*G29 -> 0 | I29: =H29/SUPUESTOS!$C$4 -> 0
A30: 5.2 | B30: Otros | C30: Materiales varios | D30: 1 | E30: Global | F30: 1 | H30: =Materiales!E6 -> 380000 | I30: =H30/SUPUESTOS!$C$4 -> 58.461538
A31: 5.3 | B31: Otros | C31: Encomienda/documentos | D31: 1 | E31: Envío | F31: 4 | G31: 30000 | H31: =D31*F31*G31 -> 120000 | I31: =H31/SUPUESTOS!$C$4 -> 18.461538
A32: 5.4 | B32: Otros | C32: Encomienda/laboratorio | D32: 1 | E32: Envío | F32: 4 | G32: 40000 | H32: =D32*F32*G32 -> 160000 | I32: =H32/SUPUESTOS!$C$4 -> 24.615385
B33: Subtotal | H33: =SUM(H29:H32) -> 660000 | I33: =H33/SUPUESTOS!$C$4 -> 101.53846 | J33: =IF(H$35=0,0,H33/H$35) -> 0.016897966
A35: TOTAL PREPARACIÓN DE CAMPO | H35: =H12+H16+H20+H27+H33 -> 39057956 | I35: =H35/SUPUESTOS!$C$4 -> 6008.9162 | J35: =1 -> 1

Sheet Laboratorio
A1: ANÁLISIS DE LABORATORIO
A2: =CONCATENATE("Calicatas: ",SUPUESTOS!C13," × ",SUPUESTOS!C14," muestras = ",SUPUESTOS!C17," | Barrenadas: ",SUPUESTOS!C15," × ",SUPUESTOS!C16," = ",SUPUESTOS!C18," | Total: ",SUPUESTOS!C19) -> Calicatas: 11 × 3 muestras = 33 | Barrenadas: 11 × 1 = 11 | Total: 44
A4: Nº | B4: Concepto | C4: Cantidad | D4: Unidad | E4: Costo unitario (Gs) | F4: Costo total (Gs) | G4: Costo total (USD)
A5: 1 | B5: Químico COMPLETO + textura | C5: =SUPUESTOS!C17 -> 33 | D5: Muestra | E5: 255000 | F5: =C5*E5 -> 8415000 | G5: =F5/SUPUESTOS!$C$4 -> 1294.6154
A6: 2 | B6: Químico Básico + textura | C6: =SUPUESTOS!C18 -> 11 | D6: Muestra | E6: 190000 | F6: =C6*E6 -> 2090000 | G6: =F6/SUPUESTOS!$C$4 -> 321.53846
A7: 3 | B7: Conductividad Eléctrica | C7: =SUPUESTOS!C17 -> 33 | D7: Muestra | E7: 55000 | F7: =C7*E7 -> 1815000 | G7: =F7/SUPUESTOS!$C$4 -> 279.23077
A8: 4 | B8: Densidad aparente | C8: =SUPUESTOS!C19 -> 44 | D8: Muestra | E8: 75000 | F8: =C8*E8 -> 3300000 | G8: =F8/SUPUESTOS!$C$4 -> 507.69231
A10: TOTAL LABORATORIO | F10: =SUM(F5:F8) -> 15620000 | G10: =F10/SUPUESTOS!$C$4 -> 2403.0769

Sheet Informe_final
A1: INFORME FINAL — HONORARIOS DE GABINETE
A3: Nº | B3: Concepto | C3: Cantidad | D3: Unidad | E3: Costo unitario (Gs) | F3: Costo total (Gs) | G3: Costo total (USD)
A4: 1 | B4: Trabajos SIG y Geoportal | C4: 1 | D4: Consultor | E4: 1000000 | F4: =C4*E4 -> 1000000 | G4: =F4/SUPUESTOS!$C$4 -> 153.84615
A5: 2 | B5: Informe técnico | C5: 2 | D5: Consultor | E5: 7000000 | F5: =C5*E5 -> 14000000 | G5: =F5/SUPUESTOS!$C$4 -> 2153.8462
A6: 3 | B6: Traducción | C6: 0 | D6: Traductor | E6: 1950000 | F6: =C6*E6 -> 0 | G6: =F6/SUPUESTOS!$C$4 -> 0
A8: TOTAL INFORME FINAL | F8: =SUM(F4:F6) -> 15000000 | G8: =F8/SUPUESTOS!$C$4 -> 2307.6923

Sheet Resumen
A1: CONSOLIDACIÓN DE COSTOS DIRECTOS | H1: ANÁLISIS DE MARGEN SOILTECH
A2: Nº | B2: Descripción | C2: Costo directo (Gs) | D2: Costo directo (USD) | E2: % | F2: Peso riesgo | H2: Total facturado (=Total proyecto) | I2: =C22 -> 88348762
A3: 1 | B3: Preparación / descripción de campo | C3: =Preparación_campo!H35 -> 39057956 | D3: =C3/SUPUESTOS!$C$4 -> 6008.9162 | E3: =IF($C$6=0,0,C3/$C$6) -> 0.56054968 | F3: 0.6 | H3: (-) Costos campo (100%) | I3: =-Preparación_campo!H35 -> -39057956
A4: 2 | B4: Análisis de laboratorio | C4: =Laboratorio!F10 -> 15620000 | D4: =C4/SUPUESTOS!$C$4 -> 2403.0769 | E4: =IF($C$6=0,0,C4/$C$6) -> 0.2241742 | F4: 0.15 | H4: (-) Costos laboratorio | I4: =-Laboratorio!F10 -> -15620000
A5: 3 | B5: Informe final y gabinete | C5: =Informe_final!F8 -> 15000000 | D5: =C5/SUPUESTOS!$C$4 -> 2307.6923 | E5: =IF($C$6=0,0,C5/$C$6) -> 0.21527612 | F5: 0.25 | H5: (-) Costos informe final | I5: =-Informe_final!F8 -> -15000000
B6: SUBTOTAL COSTOS DIRECTOS | C6: =SUM(C3:C5) -> 69677956 | D6: =C6/SUPUESTOS!$C$4 -> 10719.685 | E6: =SUM(F3:F5) -> 1 | F6: =SUM(F3:F5) -> 1 | H6: (=) Margen bruto | I6: =I2+I3+I4+I5 -> 18670806
H7: Margen bruto (%) | I7: =IF(I2=0,0,I6/I2) -> 0.21133071
A8: IMPREVISTO PONDERADO POR RIESGO | H8: Margen bruto (USD) | I8: =I6/SUPUESTOS!$C$4 -> 2872.4317
A9: Nº | B9: Rubro | C9: Base imponible | D9: Peso riesgo | E9: Imprevisto asignado (Gs) | F9: Imprevisto asignado (USD)
A10: 1 | B10: Preparación campo | C10: =C3 -> 39057956 | D10: =F3 -> 0.6 | E10: =$C$6*SUPUESTOS!$C$5*(F3/$F$6) -> 4180677.3 | F10: =E10/SUPUESTOS!$C$4 -> 643.18113 | H10: RATIOS DEL PROYECTO
A11: 2 | B11: Laboratorio | C11: =C4 -> 15620000 | D11: =F4 -> 0.15 | E11: =$C$6*SUPUESTOS!$C$5*(F4/$F$6) -> 1045169.3 | F11: =E11/SUPUESTOS!$C$4 -> 160.79528 | H11: Costo / hectárea (USD) | I11: =D22/SUPUESTOS!C20 -> 6.7960586
A12: 3 | B12: Informe final | C12: =C5 -> 15000000 | D12: =F5 -> 0.25 | E12: 0 | F12: =E12/SUPUESTOS!$C$4 -> 0 | H12: Costo / calicata (USD) | I12: =D22/SUPUESTOS!C13 -> 1235.647
B13: TOTAL IMPREVISTO | C13: =C6 -> 69677956 | D13: =SUM(D10:D12) -> 1 | E13: =SUM(E10:E12) -> 5225846.7 | F13: =E13/SUPUESTOS!$C$4 -> 803.97641 | H13: Costo / muestra total (USD) | I13: =D22/SUPUESTOS!C19 -> 308.91175
H14: Costo lab / muestra (USD) | I14: =Laboratorio!G10/SUPUESTOS!C19 -> 54.615385
H15: Densidad muestreo (ha/calicata) | I15: =SUPUESTOS!C21 -> 181.81818
A16: CÁLCULO DEL MONTO FINAL
B17: Subtotal costos directos | C17: =C6 -> 69677956 | D17: =C17/SUPUESTOS!$C$4 -> 10719.685
B18: Imprevisto ponderado | C18: =E13 -> 5225846.7 | D18: =C18/SUPUESTOS!$C$4 -> 803.97641
B19: Subtotal con imprevisto | C19: =C17+C18 -> 74903802 | D19: =C19/SUPUESTOS!$C$4 -> 11523.662
B20: =CONCATENATE("Retención IVA (",TEXT(SUPUESTOS!C6,"0%"),")") -> Retención IVA (7%) | C20: =C19*SUPUESTOS!C6 -> 5243266.2 | D20: =C20/SUPUESTOS!$C$4 -> 806.65633
B21: Margen | C21: =+SUM(C3:C4)*0.15 -> 8201693.3 | D21: =C21/SUPUESTOS!$C$4 -> 1261.799
B22: TOTAL PROYECTO | C22: =C19+C20+C21 -> 88348762 | D22: =C22/SUPUESTOS!$C$4 -> 13592.117
B23: MONTO A SOLICITAR (USD) | D23: =ROUNDUP(D22,-2) -> 13600
A26: DETALLE PARA PROPUESTA AL CLIENTE
B27: Descripción del servicio | C27: Costo (Gs) | D27: Costo (USD)
A28: a) | B28: Preparación de calicatas, descripción y muestreos, resistencia a la penetración. | C28: =C3+E10+C21+(C3+E10)/$C$19*C20 -> 54467031 | D28: =ROUNDUP(C28/SUPUESTOS!$C$4,-2) -> 8400
A29: b) | B29: Análisis de Laboratorio con determinaciones químicas y físicas. | C29: =C4+E11+(C4+E11)/$C$19*C20 -> 17831731 | D29: =ROUNDUP(C29/SUPUESTOS!$C$4,-2) -> 2800
A30: c) | B30: Informe final, humedales, carbono orgánico, degradación, descripciones detalladas, cartografía. | C30: =C5+E12+(C5+E12)/$C$19*C20 -> 16050000 | D30: =ROUNDUP(C30/SUPUESTOS!$C$4,-2) -> 2500
B31: TOTAL (verificación = Total proyecto) | C31: =SUM(C28:C30) -> 88348762 | D31: =+SUM(D28:D30) -> 13700

Sheet Flujo_hitos
A1: FLUJO DE CAJA — ESTRUCTURA 50/50
B3: Concepto | C3: Anticipo (50%) Inicio del proyecto | D3: Saldo (50%) Contra entrega | E3: TOTAL
A4: INGRESOS (cobro al cliente)
B5: % del monto total | C5: =SUPUESTOS!C7 -> 0.5 | D5: =SUPUESTOS!C8 -> 0.5 | E5: =C5+D5 -> 1
B6: Monto cobrado (Gs) | C6: =Resumen!C22*C5 -> 44174381 | D6: =Resumen!C22*D5 -> 44174381 | E6: =C6+D6 -> 88348762
B7: Monto cobrado (USD) | C7: =C6/SUPUESTOS!$C$4 -> 6796.0586 | D7: =D6/SUPUESTOS!$C$4 -> 6796.0586 | E7: =E6/SUPUESTOS!$C$4 -> 13592.117
A9: EGRESOS (costos por tramo)
B10: Honorarios campo | C10: =Preparación_campo!H12 -> 24700000 | D10: 0 | E10: =C10+D10 -> 24700000
B11: Movilidad + combustible | C11: =Preparación_campo!H16 -> 7534400 | D11: 0 | E11: =C11+D11 -> 7534400
B12: Viáticos + hospedaje | C12: =Preparación_campo!H20 -> 4000000 | D12: 0 | E12: =C12+D12 -> 4000000
B13: Equipos de campo | C13: =Preparación_campo!H27 -> 2163555.6 | D13: 0 | E13: =C13+D13 -> 2163555.6
B14: Otros gastos de campo | C14: =Preparación_campo!H33 -> 660000 | D14: 0 | E14: =C14+D14 -> 660000
B15: Laboratorio | C15: =Laboratorio!F10 -> 15620000 | D15: 0 | E15: =C15+D15 -> 15620000
B16: Informe final + gabinete | C16: 0 | D16: =Informe_final!F8 -> 15000000 | E16: =C16+D16 -> 15000000
B18: TOTAL EGRESOS | C18: =SUM(C10:C16) -> 54677956 | D18: =SUM(D10:D16) -> 15000000 | E18: =C18+D18 -> 69677956
A20: POSICIÓN DE CAJA
B21: Saldo del tramo (Gs) | C21: =C6-C18 -> -10503575 | D21: =D6-D18 -> 29174381 | E21: =C21+D21 -> 18670806
B22: Saldo acumulado (Gs) | C22: =C21 -> -10503575 | D22: =C22+D21 -> 18670806 | E22: =D22 -> 18670806
B23: Saldo acumulado (USD) | C23: =C22/SUPUESTOS!$C$4 -> -1615.9346 | D23: =D22/SUPUESTOS!$C$4 -> 2872.4317 | E23: =E22/SUPUESTOS!$C$4 -> 2872.4317
A25: NECESIDAD DE CAPITAL DE TRABAJO
B26: Déficit máximo del proyecto (Gs) | C26: =MIN(C22,D22,0) -> -10503575 | D26: ← Monto que SoilTech financia con capital propio
B27: Déficit máximo (USD) | C27: =C26/SUPUESTOS!$C$4 -> -1615.9346
B28: Recuperación del capital en tramo 2 | C28: =D22 -> 18670806
B30: Margen final (= saldo acumulado final) | C30: =E22 -> 18670806 | D30: =C30/SUPUESTOS!$C$4 -> 2872.4317

Sheet Equipos
A1: # | B1: Equipo | C1: Costo adquisición | D1: Vida útil (meses) | E1: Costo uso/mes
A2: 1 | B2: Penetrómetro | C2: 6240000 | D2: 60 | E2: =IF(D2=0,0,C2/D2) -> 104000
A3: 2 | B3: Dron | C3: 8000000 | D3: 60 | E3: =IF(D3=0,0,C3/D3) -> 133333.33
A4: 3 | B4: Cámara digital | C4: 3000000 | D4: 60 | E4: =IF(D4=0,0,C4/D4) -> 50000
A5: 4 | B5: Tablet | C5: 2200000 | D5: 36 | E5: =IF(D5=0,0,C5/D5) -> 61111.111

Sheet Materiales
A1: # | B1: Descripción | C1: Cantidad | D1: Precio unitario | E1: Costo
A2: 1 | B2: Bolsa | C2: 10 | D2: 20000 | E2: =C2*D2 -> 200000
A3: 2 | B3: Grampas | C3: 10 | D3: 5000 | E3: =C3*D3 -> 50000
A4: 3 | B4: Pizarra | C4: 1 | D4: 80000 | E4: =C4*D4 -> 80000
A5: 4 | B5: Papel film | C5: 1 | D5: 50000 | E5: =C5*D5 -> 50000
B6: TOTAL | E6: =SUM(E2:E5) -> 380000

Sheet Hoja1
A1: DETALLE | B1: MONTO USD | C1: PLAN DE PAGO
A2: workspace | B2: 15 | C2: mensual
A3: claude | B3: 17 | C3: mensual
A4: gemini | B4: 20 | C4: mensual
A5: microsoft | B5: 5 | C5: mensual
A6: dominio | B6: 12 | C6: anual
A7: arcgis | B7: 1000 | C7: anual
A8: internet | B8: 30 | C8: mensual
A9: mantenimiento notebook | B9: 100 | C9: anual
